CHANGELOG.rst
MANIFEST.in
README.rst
setup.py
dehydrate/__init__.py
dehydrate/base.py
dehydrate/exceptions.py
dehydrate/handlers.py
dehydrate/helpers.py
dehydrate/shortcuts.py
dehydrate/spec.py
dehydrate.egg-info/PKG-INFO
dehydrate.egg-info/SOURCES.txt
dehydrate.egg-info/dependency_links.txt
dehydrate.egg-info/requires.txt
dehydrate.egg-info/top_level.txt